setup.py
micropython_uasyncio.queues.egg-info/PKG-INFO
micropython_uasyncio.queues.egg-info/SOURCES.txt
micropython_uasyncio.queues.egg-info/dependency_links.txt
micropython_uasyncio.queues.egg-info/requires.txt
micropython_uasyncio.queues.egg-info/top_level.txt
uasyncio/queues.py